manage_celery_callback_server.py
celery_callback_server/__init__.py
celery_callback_server/asgi.py
celery_callback_server/settings.py
celery_callback_server/urls.py
celery_callback_server/wsgi.py
celery_callback_service/__init__.py
celery_callback_service/actions.py
celery_callback_service/admin.py
celery_callback_service/apps.py
celery_callback_service/celery_tasks.py
celery_callback_service/client.py
celery_callback_service/constants.py
celery_callback_service/forms.py
celery_callback_service/models.py
celery_callback_service/services.py
celery_callback_service/settings.py
celery_callback_service/tests.py
celery_callback_service/urls.py
celery_callback_service/utils.py
celery_callback_service/views.py
celery_callback_service/migrations/0001_initial.py
celery_callback_service/migrations/0002_alter_task_options_task_error_data_and_more.py
celery_callback_service/migrations/0003_remove_task_done_time_remove_task_ready_time_and_more.py
celery_callback_service/migrations/0004_alter_task_options.py
celery_callback_service/migrations/__init__.py
celery_callback_service-0.1.8.dist-info/LICENSE
celery_callback_service-0.1.8.dist-info/METADATA
celery_callback_service-0.1.8.dist-info/WHEEL
celery_callback_service-0.1.8.dist-info/entry_points.txt
celery_callback_service-0.1.8.dist-info/top_level.txt
celery_callback_service-0.1.8.dist-info/RECORD
