Metadata-Version: 2.1
Name: celery-callback-service
Version: 0.1.8
Summary: 基于celery的回调服务。业务系统创建celery回调任务，celery-callback-worker执行回调任务，业务系统在回调任务中处理异步任务。
Author: Sun XiaoWei
Maintainer: Sun XiaoWei
License: MIT
Keywords: celery callback service
Classifier: Development Status :: 5 - Production/Stable
Classifier: Intended Audience :: Developers
Classifier: Topic :: Software Development :: Libraries :: Python Modules
Classifier: License :: OSI Approved :: MIT License
Classifier: Programming Language :: Python :: 3
Classifier: Programming Language :: Python :: 3 :: Only
License-File: LICENSE
Requires-Dist: django
Requires-Dist: django-admin-daterange-listfilter
Requires-Dist: django-model-helper>=0.1.12
Requires-Dist: django-horizontal-list-filter
Requires-Dist: django-checkbox-normalize
Requires-Dist: django-app-requires
Requires-Dist: django-apis>=0.2.10
Requires-Dist: celery
Requires-Dist: celery-debug
Requires-Dist: redis
Requires-Dist: pwgen
Requires-Dist: zenutils
Requires-Dist: globallock
Requires-Dist: requests
Requires-Dist: hybrid-cipher
